netbox_ipcalculator/__init__.py
netbox_ipcalculator/navigation.py
netbox_ipcalculator/pluginvars.json
netbox_ipcalculator/template_content.py
netbox_ipcalculator/urls.py
netbox_ipcalculator/views.py
netbox_ipcalculator/migrations/__init__.py
netbox_ipcalculator/static/netbox_ipcalculator/jquery-3.6.0.min.js
netbox_ipcalculator/templates/netbox_ipcalculator/ipcalcbase.html
netbox_ipcalculator/templates/netbox_ipcalculator/core/ipcalc.html
netbox_ipcalculator/templates/netbox_ipcalculator/core/ipcalc.js
netbox_ipcalculator/templates/netbox_ipcalculator/core/subnets.html
netbox_ipcalculator-1.4.11.dist-info/licenses/LICENSE
netbox_ipcalculator-1.4.11.dist-info/METADATA
netbox_ipcalculator-1.4.11.dist-info/WHEEL
netbox_ipcalculator-1.4.11.dist-info/top_level.txt
netbox_ipcalculator-1.4.11.dist-info/RECORD
