Metadata-Version: 2.4
Name: netbox_ipcalculator
Version: 1.4.11
Summary: Netbox IP Calculator and Subnet Splitter
Home-page: https://github.com/PieterL75/netbox_ipcalculator
Author: Pieter Lambrecht
License: Apache 2.0
License-File: LICENSE
Dynamic: author
Dynamic: description
Dynamic: description-content-type
Dynamic: home-page
Dynamic: license
Dynamic: license-file
Dynamic: summary
